Workbook

Sheet Summary
A1: Estimating Walmart's cost of capital: summary of results
A2: Prepared by Paolo Safady, October 21, 2026. Figures in $ millions unless noted.
A4: Measure | B4: Value | C4: Question | D4: Sheet
A5: Total debt (total liabilities), $M | B5: ='Q2 Financing Sources'!B18 -> 139661 | C5: Q2 | D5: Q2 Financing Sources
A6: Total equity, $M | B6: ='Q2 Financing Sources'!B26 -> 79634 | C6: Q2 | D6: Q2 Financing Sources
A7: Total financing, $M | B7: ='Q2 Financing Sources'!B28 -> 219295 | C7: Q2 | D7: Q2 Financing Sources
A8: Pre-tax cost of long-term debt | B8: ='Q3 Cost of Debt'!B10 -> 0.0353 | C8: Q3 | D8: Q3 Cost of Debt
A9: Cost of equity (CAPM) | B9: ='Q4 Cost of Equity'!B12 -> 0.106091 | C9: Q4 | D9: Q4 Cost of Equity
A10: Weight of debt | B10: ='Q5 Capital Structure'!D5 -> 0.63686359 | C10: Q5 | D10: Q5 Capital Structure
A11: Weight of equity | B11: ='Q5 Capital Structure'!D6 -> 0.36313641 | C11: Q5 | D11: Q5 Capital Structure
A12: Debt-to-equity ratio | B12: ='Q5 Capital Structure'!B10 -> 1.7537861 | C12: Q5 | D12: Q5 Capital Structure
A13: Weighted average cost of capital (WACC) | B13: ='Q6-Q7 WACC & MARR'!B15 -> 0.054936843 | C13: Q6 | D13: Q6-Q7 WACC & MARR
A14: MARR (hurdle rate) | B14: ='Q6-Q7 WACC & MARR'!B17 -> 0.054936843 | C14: Q7 | D14: Q6-Q7 WACC & MARR
A17: Color key
A18: Blue text: input taken from the Walmart case study
A19: Black text: formula calculated on the same sheet
A20: Green text: value linked from another sheet
A21: Yellow fill: key result

Sheet Q2 Financing Sources
A1: Question 2: Walmart sources of financing
A2: All figures in $ millions. Source: balance sheet provided with the Walmart case study.
A4: Line item | B4: Amount ($M) | C4: % of total financing | D4: Notes
A5: Short-term debt (current liabilities)
A6: Accounts payable | B6: 47060 | C6: =B6/$B$28 -> 0.21459678
A7: Short-term borrowings | B7: 5225 | C7: =B7/$B$28 -> 0.023826353
A8: Accrued liabilities | B8: 22159 | C8: =B8/$B$28 -> 0.10104654
A9: Current portion of long-term debt and capital leases | B9: 2605 | C9: =B9/$B$28 -> 0.011878976
A10: Other current liabilities | B10: 428 | C10: =B10/$B$28 -> 0.0019517089
A11: Total current liabilities | B11: =SUM(B6:B10) -> 77477 | C11: =B11/$B$28 -> 0.35330035
A13: Long-term debt
A14: Long-term debt and capital leases | B14: 50203 | C14: =B14/$B$28 -> 0.22892907 | D14: Mostly bonds
A15: Deferred income taxes and other | B15: 11981 | C15: =B15/$B$28 -> 0.054634169
A16: Total long-term liabilities | B16: =SUM(B14:B15) -> 62184 | C16: =B16/$B$28 -> 0.28356324
A18: Total debt (total liabilities) | B18: =B11+B16 -> 139661 | C18: =B18/$B$28 -> 0.63686359 | D18: Current + long-term liabilities
A20: Equity financing
A21: Common stock and paid-in capital | B21: 3253 | C21: =B21/$B$28 -> 0.0148339
A22: Retained earnings | B22: 80785 | C22: =B22/$B$28 -> 0.36838505
A23: Accumulated other comprehensive income (loss) | B23: -11542 | C23: =B23/$B$28 -> -0.052632299
A24: Total Walmart shareholders' equity | B24: =SUM(B21:B23) -> 72496 | C24: =B24/$B$28 -> 0.33058665
A25: Noncontrolling interest | B25: 7138 | C25: =B25/$B$28 -> 0.032549762
A26: Total equity | B26: =B24+B25 -> 79634 | C26: =B26/$B$28 -> 0.36313641 | D26: Shareholders' equity + noncontrolling interest
A28: Total financing (debt + equity) | B28: =B18+B26 -> 219295 | C28: =B28/$B$28 -> 1
A30: Total liabilities and equity per balance sheet | B30: 219295
A31: Check: difference (should be zero) | B31: =B28-B30 -> 0

Sheet Q3 Cost of Debt
A1: Question 3: Cost of long-term debt
A2: All figures in $ millions unless noted.
A4: Long-term liability | B4: Amount ($M) | C4: % of long-term liabilities | D4: Used for cost of debt? | E4: Notes
A5: Long-term debt and capital leases | B5: ='Q2 Financing Sources'!B14 -> 50203 | C5: =B5/$B$7 -> 0.80732986 | D5: Yes | E5: Mostly bonds, so the bond yield sets the cost
A6: Deferred income taxes and other | B6: ='Q2 Financing Sources'!B15 -> 11981 | C6: =B6/$B$7 -> 0.19267014 | D6: No | E6: Not bonds; no market yield
A7: Total long-term liabilities | B7: =SUM(B5:B6) -> 62184 | C7: =B7/$B$7 -> 1
A9: Cost of long-term debt | B9: Value | E9: Source
A10: Pre-tax cost of long-term debt (yield on Walmart's bonds) | B10: 0.0353 | E10: Walmart case study

Sheet Q4 Cost of Equity
A1: Question 4: Cost of equity (Capital Asset Pricing Model)
A2: Ke = Rf + β × MRP
A4: Input | B4: Value | C4: Source
A5: Beta, β (adjusted) | B5: 0.71 | C5: Walmart case study
A6: Risk-free rate, Rf (current 10-year Treasury bond yield) | B6: 0.0265 | C6: Walmart case study
A7: S&P 500 return, 2009–2018 | B7: 0.1349 | C7: Walmart case study
A8: 10-year government bond rate, 2009–2018 | B8: 0.0228 | C8: Walmart case study
A10: Calculation | B10: Value | C10: Formula
A11: Market risk premium, MRP | B11: =B7-B8 -> 0.1121 | C11: S&P 500 return − 10-year government bond rate
A12: Cost of equity, Ke | B12: =B6+B5*B11 -> 0.106091 | C12: Rf + β × MRP
A14: MRP uses the last 10 years (2009–2018) because that period is the most accurate reflection of current market conditions.

Sheet Q5 Capital Structure
A1: Question 5: Revised sources of financing and debt-to-equity ratio
A2: All figures in $ millions unless noted. Debt is total liabilities.
A4: Source of financing | B4: Amount ($M) | C4: Cost | D4: Weight (% of total)
A5: Debt (total liabilities) | B5: ='Q2 Financing Sources'!B18 -> 139661 | C5: ='Q3 Cost of Debt'!B10 -> 0.0353 | D5: =B5/$B$7 -> 0.63686359
A6: Equity (total equity) | B6: ='Q2 Financing Sources'!B26 -> 79634 | C6: ='Q4 Cost of Equity'!B12 -> 0.106091 | D6: =B6/$B$7 -> 0.36313641
A7: Total | B7: =B5+B6 -> 219295 | D7: =D5+D6 -> 1
A9: Ratio | B9: Value | C9: Formula
A10: Debt-to-equity ratio | B10: =B5/B6 -> 1.7537861 | C10: Debt ÷ Equity
A11: Debt-to-equity ratio (as a percent) | B11: =B10 -> 1.7537861

Sheet Q6-Q7 WACC & MARR
A1: Questions 6 and 7: Weighted average cost of capital and MARR
A2: WACC = We × Ke + Wd × Kd × (1 − t)
A4: Input | B4: Value | C4: Source
A5: Weight of equity, We | B5: ='Q5 Capital Structure'!D6 -> 0.36313641 | C5: Question 5
A6: Cost of equity, Ke | B6: ='Q4 Cost of Equity'!B12 -> 0.106091 | C6: Question 4
A7: Weight of debt, Wd | B7: ='Q5 Capital Structure'!D5 -> 0.63686359 | C7: Question 5
A8: Pre-tax cost of debt, Kd | B8: ='Q3 Cost of Debt'!B10 -> 0.0353 | C8: Question 3
A9: Effective tax rate, t | B9: 0.27 | C9: Walmart case study
A11: Calculation | B11: Value | C11: Formula
A12: After-tax cost of debt | B12: =B8*(1-B9) -> 0.025769 | C12: Kd × (1 − t)
A13: Equity component | B13: =B5*B6 -> 0.038525505 | C13: We × Ke
A14: Debt component | B14: =B7*B12 -> 0.016411338 | C14: Wd × Kd × (1 − t)
A15: WACC | B15: =B13+B14 -> 0.054936843 | C15: Equity component + debt component
A17: MARR (hurdle rate) | B17: =B15 -> 0.054936843 | C17: Set equal to WACC, the cost of using capital
